{
    "forms": {
        "title": "FORMS",
        "links": [
            {
                "to": "/ctzcomp",
                "text": "CtzComp"
            }, {
                "to": "/ctzvta",
                "text": "CtzVta"
            }, {
                "to": "/sido",
                "text": "SiDo"
            }, {
                "to": "/follow",
                "text": "Follow"
            }
        ]
    },
    "tables": {
        "title": "TABLES",
        "links": [
            {
                "to": "/tables/etapas",
                "text": "Etapas"
            }, {
                "to": "/tables/estados",
                "text": "Estados"
            }, {
                "to": "/tables/rutas",
                "text": "Rutas"
            }, {
                "to": "/tables/servicios",
                "text": "Servicios"
            }, {
                "to": "/tables/subservicios",
                "text": "Subservicios"
            }, {
                "to": "/tables/terceros",
                "text": "Terceros"
            }, {
                "to": "/tables/aeroptos",
                "text": "Aeroptos"
            }
        ]
    }
}